logcabin-0.1b10.dist-info/WHEEL
logcabin-0.1b10.dist-info/top_level.txt
logcabin-0.1b10.dist-info/entry_points.txt
logcabin-0.1b10.dist-info/METADATA
logcabin-0.1b10.dist-info/RECORD
logcabin/__init__.py
logcabin/configuration.py
logcabin/flow.py
logcabin/context.py
logcabin/event.py
logcabin/__main__.py
logcabin/util.py
logcabin/pipeline.py
logcabin/logging.cfg
logcabin/common.py
logcabin/statistics.py
logcabin/filters/__init__.py
logcabin/filters/stats.py
logcabin/filters/python.py
logcabin/filters/regex.py
logcabin/filters/filter.py
logcabin/filters/json.py
logcabin/filters/noop.py
logcabin/filters/syslog.py
logcabin/filters/mutate.py
logcabin/inputs/__init__.py
logcabin/inputs/file.py
logcabin/inputs/zeromq.py
logcabin/inputs/udp.py
logcabin/inputs/input.py
logcabin/outputs/__init__.py
logcabin/outputs/output.py
logcabin/outputs/log.py
logcabin/outputs/graphite.py
logcabin/outputs/file.py
logcabin/outputs/zeromq.py
logcabin/outputs/elasticsearch.py
logcabin/outputs/perf.py
logcabin/outputs/s3.py
logcabin/outputs/mongodb.py
logcabin-0.1b10.data/scripts/logcabin
