Metadata-Version: 2.0
Name: logcabin
Version: 0.1b10
Summary: Logging framework for receiving and processing events from a diverse range of sources and formats, and relaying onto multiple destinations.
Home-page: http://github.com/artirix/logcabin/
Author: Barnaby Gray
Author-email: barnaby@artirix.com
License: Apache 2.0
Platform: UNKNOWN
Requires-Dist: python-dateutil
Requires-Dist: gevent (>=0.13.6)
